img2pdf.py
jp2.py
buildr_img2pdf-0.3.1.dist-info/METADATA
buildr_img2pdf-0.3.1.dist-info/RECORD
buildr_img2pdf-0.3.1.dist-info/WHEEL
buildr_img2pdf-0.3.1.dist-info/entry_points.txt
buildr_img2pdf-0.3.1.dist-info/top_level.txt
buildr_img2pdf-0.3.1.dist-info/zip-safe
